nerodia/__init__.py
nerodia/adjacent.py
nerodia/after_hooks.py
nerodia/alert.py
nerodia/browser.py
nerodia/capabilities.py
nerodia/cell_container.py
nerodia/container.py
nerodia/cookies.py
nerodia/element_collection.py
nerodia/exception.py
nerodia/has_window.py
nerodia/html_attributes.py
nerodia/js_execution.py
nerodia/js_snippet.py
nerodia/logger.py
nerodia/meta_elements.py
nerodia/module_mapping.py
nerodia/row_container.py
nerodia/screenshot.py
nerodia/svg_attributes.py
nerodia/tag_map.py
nerodia/user_editable.py
nerodia/window.py
nerodia/elements/__init__.py
nerodia/elements/area.py
nerodia/elements/button.py
nerodia/elements/cell.py
nerodia/elements/check_box.py
nerodia/elements/d_list.py
nerodia/elements/date_field.py
nerodia/elements/date_time_field.py
nerodia/elements/element.py
nerodia/elements/file_field.py
nerodia/elements/font.py
nerodia/elements/form.py
nerodia/elements/hidden.py
nerodia/elements/html_elements.py
nerodia/elements/i_frame.py
nerodia/elements/image.py
nerodia/elements/input.py
nerodia/elements/link.py
nerodia/elements/list.py
nerodia/elements/option.py
nerodia/elements/radio.py
nerodia/elements/radio_set.py
nerodia/elements/row.py
nerodia/elements/scroll.py
nerodia/elements/select.py
nerodia/elements/svg_elements.py
nerodia/elements/table.py
nerodia/elements/table_cell.py
nerodia/elements/table_data_cell.py
nerodia/elements/table_row.py
nerodia/elements/table_section.py
nerodia/elements/text_area.py
nerodia/elements/text_field.py
nerodia/js_snippets/attributeValues.js
nerodia/js_snippets/backgroundColor.js
nerodia/js_snippets/elementObscured.js
nerodia/js_snippets/fireEvent.js
nerodia/js_snippets/focus.js
nerodia/js_snippets/getElementTags.js
nerodia/js_snippets/getInnerHtml.js
nerodia/js_snippets/getInnerText.js
nerodia/js_snippets/getOuterHtml.js
nerodia/js_snippets/getTextContent.js
nerodia/js_snippets/isImageLoaded.js
nerodia/js_snippets/selectOptionsLabel.js
nerodia/js_snippets/selectOptionsText.js
nerodia-0.14.1.dist-info/LICENSE
nerodia-0.14.1.dist-info/METADATA
nerodia-0.14.1.dist-info/WHEEL
nerodia-0.14.1.dist-info/top_level.txt
nerodia-0.14.1.dist-info/RECORD
