Metadata-Version: 2.1
Name: nerodia
Version: 0.14.1
Summary: Python port of WATIR https://github.com/watir/watir
Home-page: https://github.com/watir/nerodia
Author: Lucas Tierney
Author-email: lucast1533@gmail.com
License: MIT
Platform: UNKNOWN
Classifier: Intended Audience :: Developers
Classifier: Operating System :: POSIX
Classifier: Operating System :: Microsoft :: Windows
Classifier: Operating System :: MacOS :: MacOS X
Classifier: Topic :: Software Development :: Testing
Classifier: Topic :: Software Development :: Libraries
Classifier: Programming Language :: Python
Classifier: Programming Language :: Python :: 2.7
Classifier: Programming Language :: Python :: 3.4
Classifier: Programming Language :: Python :: 3.5
Classifier: Programming Language :: Python :: 3.6
Classifier: Programming Language :: Python :: 3.7
Requires-Dist: selenium
Requires-Dist: six
Requires-Dist: python-dateutil
